chained_aws_lambda-0.0.8.data/data/share/chained-aws-lambda/templates/app.py.jinja
chained_aws_lambda-0.0.8.data/data/share/chained-aws-lambda/templates/policy.json.jinja
chained_aws_lambda-0.0.8.data/data/share/chained-aws-lambda/templates/policy.json.jinja.orig
chained_aws_lambda-0.0.8.data/scripts/chained_aws_lambda.py
chained_aws_lambda-0.0.8.data/scripts/get_all_chained_aws_lambda_clients.py
chained_aws_lambda-0.0.8.dist-info/DESCRIPTION.rst
chained_aws_lambda-0.0.8.dist-info/METADATA
chained_aws_lambda-0.0.8.dist-info/RECORD
chained_aws_lambda-0.0.8.dist-info/WHEEL
chained_aws_lambda-0.0.8.dist-info/metadata.json
chained_aws_lambda-0.0.8.dist-info/top_level.txt
chainedawslambda/__init__.py
chainedawslambda/_awsimpl.py
chainedawslambda/_awstest.py
chainedawslambda/aws.py
chainedawslambda/awsconstants.py
chainedawslambda/base.py
chainedawslambda/constants.py
chainedawslambda/runner.py
chainedawslambda/s3copyclient.py
chainedawslambda/blobstore/__init__.py
chainedawslambda/blobstore/s3.py
chainedawslambda/util/__init__.py
chainedawslambda/util/aws/__init__.py
chainedawslambda/util/aws/_boto3_loader.py
chainedawslambda/util/aws/clients.py
chainedawslambda/util/aws/logging.py
chainedawslambda/util/aws/resources.py
