Metadata-Version: 2.0
Name: chained-aws-lambda
Version: 0.0.8
Summary: chain work using AWS lambdas
Home-page: https://github.com/chanzuckerberg/chained-aws-lambda
Author: Human Cell Atlas contributors
Author-email: tonytung@chanzuckerberg.com
License: Apache Software License
Platform: MacOS X
Platform: Posix
Classifier: Intended Audience :: Developers
Classifier: License :: OSI Approved :: Apache Software License
Classifier: Operating System :: MacOS :: MacOS X
Classifier: Operating System :: POSIX
Classifier: Programming Language :: Python
Classifier: Programming Language :: Python :: 3.6
Classifier: Topic :: Software Development :: Libraries :: Python Modules
Requires-Dist: boto3
Requires-Dist: cloud-blobstore
Requires-Dist: jinja2
Requires-Dist: requests
